dcnnt/__init__.py
dcnnt/app.py
dcnnt/dcnnt.py
dcnnt/device_manager.py
dcnnt/server_search.py
dcnnt/tcp_server.py
dcnnt/common/__init__.py
dcnnt/common/daemon.py
dcnnt/common/jsonconf.py
dcnnt/common/jsonrpc.py
dcnnt/plugins/__init__.py
dcnnt/plugins/base.py
dcnnt/plugins/file_transfer.py
dcnnt/plugins/notifications.py
dcnnt/plugins/opener.py
dcnnt/plugins/remote_commands.py
dcnnt/plugins/sync.py
dcnnt-0.10.0.dist-info/LICENSE
dcnnt-0.10.0.dist-info/METADATA
dcnnt-0.10.0.dist-info/WHEEL
dcnnt-0.10.0.dist-info/entry_points.txt
dcnnt-0.10.0.dist-info/top_level.txt
dcnnt-0.10.0.dist-info/RECORD
