Metadata-Version: 2.1
Name: dcnnt
Version: 0.10.0
Summary: UI-less tool to connect Android phone with desktop
Home-page: https://github.com/cyanomiko/dcnnt-py
Author: cyanomiko
Author-email: cyanomiko@protonmail.com
License: MIT
Keywords: phone,android,sync,device
Classifier: Development Status :: 4 - Beta
Classifier: Environment :: No Input/Output (Daemon)
Classifier: Intended Audience :: End Users/Desktop
Classifier: License :: OSI Approved :: MIT License
Classifier: Operating System :: POSIX :: Linux
Classifier: Programming Language :: Python :: 3
Classifier: Topic :: Communications :: File Sharing
Classifier: Topic :: System :: Networking
Requires-Python: >=3.7
License-File: LICENSE
Requires-Dist: pycryptodome >=3.9.3
